{
    "title": "The Story of the Three Little Pigs",
    "summary": [
        "<p><b>1. Location A (the first Pig's house)</b><br>A little Pig builds a house of straw, but a Wolf blows it down and eats him.</p>",
        "<p><b>2. Location B (the second Pig's house)</b><br>A second Pig builds a house of furze, but the Wolf blows it down and eats him too.</p>",
        "<p><b>3. Location C (the third Pig's house)</b><br>A third Pig builds a house of bricks, which the Wolf cannot blow down. The Wolf tries to trick the Pig into going to a field of turnips, but the Pig outsmarts him.</p>",
        "<p><b>4. Location D (Mr. Smith's home-field)</b><br>The Pig tells the Wolf that he already got the turnips.</p>",
        "<p><b>5. Location E (Merry-garden)</b><br>The Wolf tries to trick the Pig again with an apple-tree, but the Pig gets there first and escapes by throwing an apple far away.</p>",
        "<p><b>6. Location F (the Town)</b><br>The Wolf invites the Pig to a Fair, but the Pig goes earlier and buys a butter churn. He hides in it and rolls down the hill, scaring the Wolf away.</p>",
        "<p><b>7. Location G (the hill)</b><br>The Pig tells the Wolf that he was the one in the butter churn that rolled down the hill.</p>",
        "<p><b>8. Location C (the third Pig's house)</b><br>The Wolf tries to get into the Pig's house through the chimney, but the Pig boils him in a pot of water and eats him. The Pig lives happily ever after.</p>"
    ],
    "nodes": [
        {
            "id": "An old Sow",
            "label": "An old Sow",
            "shape": "box",
            "period": [
                1
            ],
            "size": 20
        },
        {
            "id": "Three little Pigs",
            "label": "Three little Pigs",
            "shape": "box",
            "period": [
                1
            ],
            "size": 20
        },
        {
            "id": "A house of straw",
            "label": "A house of straw",
            "shape": "box",
            "period": [
                1
            ],
            "size": 20
        },
        {
            "id": "A Wolf",
            "label": "A Wolf",
            "shape": "box",
            "period": [
                1,
                2,
                3,
                4
            ],
            "size": 20
        },
        {
            "id": "A door",
            "label": "A door",
            "shape": "box",
            "period": [
                1
            ],
            "size": 20
        },
        {
            "id": "The second Pig",
            "label": "The second Pig",
            "shape": "box",
            "period": [
                2
            ],
            "size": 20
        },
        {
            "id": "A Man with a bundle of furze",
            "label": "A Man with a bundle of furze",
            "shape": "box",
            "period": [
                2
            ],
            "size": 20
        },
        {
            "id": "A house of furze",
            "label": "A house of furze",
            "shape": "box",
            "period": [
                2
            ],
            "size": 20
        },
        {
            "id": "The third Pig",
            "label": "The third Pig",
            "shape": "box",
            "period": [
                3,
                4,
                5,
                6,
                7,
                8
            ],
            "size": 20
        },
        {
            "id": "A Man with a load of bricks",
            "label": "A Man with a load of bricks",
            "shape": "box",
            "period": [
                3
            ],
            "size": 20
        },
        {
            "id": "A house of bricks",
            "label": "A house of bricks",
            "shape": "box",
            "period": [
                3
            ],
            "size": 20
        },
        {
            "id": "A field of turnips",
            "label": "A field of turnips",
            "shape": "box",
            "period": [
                3
            ],
            "size": 20
        },
        {
            "id": "Mr. Smiths home-field",
            "label": "Mr. Smiths home-field",
            "shape": "box",
            "period": [
                3
            ],
            "size": 20
        },
        {
            "id": "Six oclock",
            "label": "Six oclock",
            "shape": "box",
            "period": [
                3
            ],
            "size": 20
        },
        {
            "id": "Five oclock",
            "label": "Five oclock",
            "shape": "box",
            "period": [
                3,
                5
            ],
            "size": 20
        },
        {
            "id": "A pot-full of turnips",
            "label": "A pot-full of turnips",
            "shape": "box",
            "period": [
                4
            ],
            "size": 20
        },
        {
            "id": "Dinner",
            "label": "Dinner",
            "shape": "box",
            "period": [
                4
            ],
            "size": 20
        },
        {
            "id": "The Wolf",
            "label": "The Wolf",
            "shape": "box",
            "period": [
                5,
                6,
                7,
                8
            ],
            "size": 20
        },
        {
            "id": "An apple-tree",
            "label": "An apple-tree",
            "shape": "box",
            "period": [
                5
            ],
            "size": 20
        },
        {
            "id": "Merry-garden",
            "label": "Merry-garden",
            "shape": "box",
            "period": [
                5
            ],
            "size": 20
        },
        {
            "id": "Four oclock",
            "label": "Four oclock",
            "shape": "box",
            "period": [
                5
            ],
            "size": 20
        },
        {
            "id": "Some apples",
            "label": "Some apples",
            "shape": "box",
            "period": [
                5
            ],
            "size": 20
        },
        {
            "id": "A Fair in the Town",
            "label": "A Fair in the Town",
            "shape": "box",
            "period": [
                6
            ],
            "size": 20
        },
        {
            "id": "Three oclock",
            "label": "Three oclock",
            "shape": "box",
            "period": [
                6
            ],
            "size": 20
        },
        {
            "id": "A butter churn",
            "label": "A butter churn",
            "shape": "box",
            "period": [
                6,
                7
            ],
            "size": 20
        },
        {
            "id": "A hill",
            "label": "A hill",
            "shape": "box",
            "period": [
                6,
                7
            ],
            "size": 20
        },
        {
            "id": "A great round thing",
            "label": "A great round thing",
            "shape": "box",
            "period": [
                7
            ],
            "size": 20
        },
        {
            "id": "A Fair",
            "label": "A Fair",
            "shape": "box",
            "period": [
                7
            ],
            "size": 20
        },
        {
            "id": "A chimney",
            "label": "A chimney",
            "shape": "box",
            "period": [
                8
            ],
            "size": 20
        },
        {
            "id": "A pot full of water",
            "label": "A pot full of water",
            "shape": "box",
            "period": [
                8
            ],
            "size": 20
        },
        {
            "id": "A blazing fire",
            "label": "A blazing fire",
            "shape": "box",
            "period": [
                8
            ],
            "size": 20
        },
        {
            "id": "Supper",
            "label": "Supper",
            "shape": "box",
            "period": [
                8
            ],
            "size": 20
        }
    ],
    "edges": [
        {
            "id": "The second PigtoA Wolf_2",
            "label": "refuse",
            "title": "refuse",
            "from": "The second Pig",
            "to": "A Wolf",
            "arrows": "to",
            "period": [
                2
            ],
            "smooth": {
                "type": "curvedCW",
                "roundness": 0.3
            }
        },
        {
            "id": "The third PigtoSix oclock_3",
            "label": "return home before",
            "title": "return home before",
            "from": "The third Pig",
            "to": "Six oclock",
            "arrows": "to",
            "period": [
                3
            ],
            "smooth": {
                "type": "curvedCW",
                "roundness": 0.3
            }
        },
        {
            "id": "The WolftoA Fair in the Town_6",
            "label": "run home without going to",
            "title": "run home without going to",
            "from": "The Wolf",
            "to": "A Fair in the Town",
            "arrows": "to",
            "period": [
                6
            ],
            "smooth": {
                "type": "curvedCW",
                "roundness": 0.3
            }
        },
        {
            "id": "A WolftoA field of turnips_3",
            "label": "know",
            "title": "know",
            "from": "A Wolf",
            "to": "A field of turnips",
            "arrows": "to",
            "period": [
                3
            ],
            "smooth": {
                "type": "curvedCW",
                "roundness": 0.3
            }
        },
        {
            "id": "The third PigtoThree oclock_6",
            "label": "go off before",
            "title": "go off before",
            "from": "The third Pig",
            "to": "Three oclock",
            "arrows": "to",
            "period": [
                6
            ],
            "smooth": {
                "type": "curvedCW",
                "roundness": 0.3
            }
        },
        {
            "id": "The third PigtoFour oclock_5",
            "label": "wake at",
            "title": "wake at",
            "from": "The third Pig",
            "to": "Four oclock",
            "arrows": "to",
            "period": [
                5
            ],
            "smooth": {
                "type": "curvedCW",
                "roundness": 0.3
            }
        },
        {
            "id": "The third PigtoA Fair_7",
            "label": "go to",
            "title": "go to",
            "from": "The third Pig",
            "to": "A Fair",
            "arrows": "to",
            "period": [
                7
            ],
            "smooth": {
                "type": "curvedCW",
                "roundness": 0.3
            }
        },
        {
            "id": "A WolftoSix oclock_3",
            "label": "come at",
            "title": "come at",
            "from": "A Wolf",
            "to": "Six oclock",
            "arrows": "to",
            "period": [
                3
            ],
            "smooth": {
                "type": "curvedCW",
                "roundness": 0.3
            }
        },
        {
            "id": "A WolftoThe second Pig_2",
            "label": "eat",
            "title": "eat",
            "from": "A Wolf",
            "to": "The second Pig",
            "arrows": "to",
            "period": [
                2
            ],
            "smooth": {
                "type": "curvedCW",
                "roundness": 0.3
            }
        },
        {
            "id": "The WolftoAn apple-tree_5",
            "label": "know",
            "title": "know",
            "from": "The Wolf",
            "to": "An apple-tree",
            "arrows": "to",
            "period": [
                5
            ],
            "smooth": {
                "type": "curvedCW",
                "roundness": 0.3
            }
        },
        {
            "id": "A WolftoA house of furze_2",
            "label": "blow down",
            "title": "blow down",
            "from": "A Wolf",
            "to": "A house of furze",
            "arrows": "to",
            "period": [
                2
            ],
            "smooth": {
                "type": "curvedCW",
                "roundness": 0.3
            }
        },
        {
            "id": "The WolftoA great round thing_7",
            "label": "be frightened by",
            "title": "be frightened by",
            "from": "The Wolf",
            "to": "A great round thing",
            "arrows": "to",
            "period": [
                7
            ],
            "smooth": {
                "type": "curvedCW",
                "roundness": 0.3
            }
        },
        {
            "id": "A WolftoA door_1",
            "label": "knock",
            "title": "knock",
            "from": "A Wolf",
            "to": "A door",
            "arrows": "to",
            "period": [
                1
            ],
            "smooth": {
                "type": "curvedCW",
                "roundness": 0.3
            }
        },
        {
            "id": "The WolftoA pot full of water_8",
            "label": "fall in",
            "title": "fall in",
            "from": "The Wolf",
            "to": "A pot full of water",
            "arrows": "to",
            "period": [
                8
            ],
            "smooth": {
                "type": "curvedCW",
                "roundness": 0.3
            }
        },
        {
            "id": "A great round thingtoThe Wolf_7",
            "label": "pass by",
            "title": "pass by",
            "from": "A great round thing",
            "to": "The Wolf",
            "arrows": "to",
            "period": [
                7
            ],
            "smooth": {
                "type": "curvedCW",
                "roundness": 0.3
            }
        },
        {
            "id": "The third PigtoA pot-full of turnips_4",
            "label": "get",
            "title": "get",
            "from": "The third Pig",
            "to": "A pot-full of turnips",
            "arrows": "to",
            "period": [
                4
            ],
            "smooth": {
                "type": "curvedCW",
                "roundness": 0.3
            }
        },
        {
            "id": "The third PigtoSupper_8",
            "label": "have for",
            "title": "have for",
            "from": "The third Pig",
            "to": "Supper",
            "arrows": "to",
            "period": [
                8
            ],
            "smooth": {
                "type": "curvedCW",
                "roundness": 0.3
            }
        },
        {
            "id": "A pot-full of turnipstoDinner_4",
            "label": "be for",
            "title": "be for",
            "from": "A pot-full of turnips",
            "to": "Dinner",
            "arrows": "to",
            "period": [
                4
            ],
            "smooth": {
                "type": "curvedCW",
                "roundness": 0.3
            }
        },
        {
            "id": "The third PigtoA Wolf_3",
            "label": "ask",
            "title": "ask",
            "from": "The third Pig",
            "to": "A Wolf",
            "arrows": "to",
            "period": [
                3
            ],
            "smooth": {
                "type": "curvedCW",
                "roundness": 0.3
            }
        },
        {
            "id": "The third PigtoA Wolf_4",
            "label": "reply",
            "title": "reply",
            "from": "The third Pig",
            "to": "A Wolf",
            "arrows": "to",
            "period": [
                4
            ],
            "smooth": {
                "type": "curvedCW",
                "roundness": 0.3
            }
        },
        {
            "id": "A butter churntoThe Wolf_6",
            "label": "frighten",
            "title": "frighten",
            "from": "A butter churn",
            "to": "The Wolf",
            "arrows": "to",
            "period": [
                6
            ],
            "smooth": {
                "type": "curvedCW",
                "roundness": 0.3
            }
        },
        {
            "id": "The third PigtoA house of bricks_3",
            "label": "build",
            "title": "build",
            "from": "The third Pig",
            "to": "A house of bricks",
            "arrows": "to",
            "period": [
                3
            ],
            "smooth": {
                "type": "curvedCW",
                "roundness": 0.3
            }
        },
        {
            "id": "The third PigtoA house of bricks_5",
            "label": "run home to",
            "title": "run home to",
            "from": "The third Pig",
            "to": "A house of bricks",
            "arrows": "to",
            "period": [
                5
            ],
            "smooth": {
                "type": "curvedCW",
                "roundness": 0.3
            }
        },
        {
            "id": "A field of turnipstoMr. Smiths home-field_3",
            "label": "locate in",
            "title": "locate in",
            "from": "A field of turnips",
            "to": "Mr. Smiths home-field",
            "arrows": "to",
            "period": [
                3
            ],
            "smooth": {
                "type": "curvedCW",
                "roundness": 0.3
            }
        },
        {
            "id": "The WolftoFive oclock_5",
            "label": "specify",
            "title": "specify",
            "from": "The Wolf",
            "to": "Five oclock",
            "arrows": "to",
            "period": [
                5
            ],
            "smooth": {
                "type": "curvedCW",
                "roundness": 0.3
            }
        },
        {
            "id": "The third PigtoA Fair in the Town_6",
            "label": "get to",
            "title": "get to",
            "from": "The third Pig",
            "to": "A Fair in the Town",
            "arrows": "to",
            "period": [
                6
            ],
            "smooth": {
                "type": "curvedCW",
                "roundness": 0.3
            }
        },
        {
            "id": "An apple-treetoMerry-garden_5",
            "label": "locate in",
            "title": "locate in",
            "from": "An apple-tree",
            "to": "Merry-garden",
            "arrows": "to",
            "period": [
                5
            ],
            "smooth": {
                "type": "curvedCW",
                "roundness": 0.3
            }
        },
        {
            "id": "A WolftoA house of bricks_3",
            "label": "fail to blow down",
            "title": "fail to blow down",
            "from": "A Wolf",
            "to": "A house of bricks",
            "arrows": "to",
            "period": [
                3
            ],
            "smooth": {
                "type": "curvedCW",
                "roundness": 0.3
            }
        },
        {
            "id": "The WolftoThe third Pig_5",
            "label": "ask",
            "title": "ask",
            "from": "The Wolf",
            "to": "The third Pig",
            "arrows": "to",
            "period": [
                5
            ],
            "smooth": {
                "type": "curvedCW",
                "roundness": 0.3
            }
        },
        {
            "id": "The WolftoThe third Pig_6",
            "label": "answer",
            "title": "answer",
            "from": "The Wolf",
            "to": "The third Pig",
            "arrows": "to",
            "period": [
                6
            ],
            "smooth": {
                "type": "curvedCW",
                "roundness": 0.3
            }
        },
        {
            "id": "The WolftoThe third Pig_7",
            "label": "tell",
            "title": "tell",
            "from": "The Wolf",
            "to": "The third Pig",
            "arrows": "to",
            "period": [
                7
            ],
            "smooth": {
                "type": "curvedCW",
                "roundness": 0.3
            }
        },
        {
            "id": "A butter churntoThe third Pig_6",
            "label": "have inside it",
            "title": "have inside it",
            "from": "A butter churn",
            "to": "The third Pig",
            "arrows": "to",
            "period": [
                6
            ],
            "smooth": {
                "type": "curvedCW",
                "roundness": 0.3
            }
        },
        {
            "id": "The third PigtoAn apple-tree_5",
            "label": "jump down from",
            "title": "jump down from",
            "from": "The third Pig",
            "to": "An apple-tree",
            "arrows": "to",
            "period": [
                5
            ],
            "smooth": {
                "type": "curvedCW",
                "roundness": 0.3
            }
        },
        {
            "id": "The third PigtoA pot full of water_8",
            "label": "hang on",
            "title": "hang on",
            "from": "The third Pig",
            "to": "A pot full of water",
            "arrows": "to",
            "period": [
                8
            ],
            "smooth": {
                "type": "curvedCW",
                "roundness": 0.3
            }
        },
        {
            "id": "An old SowtoThree little Pigs_1",
            "label": "send",
            "title": "send",
            "from": "An old Sow",
            "to": "Three little Pigs",
            "arrows": "to",
            "period": [
                1
            ],
            "smooth": {
                "type": "curvedCW",
                "roundness": 0.3
            }
        },
        {
            "id": "The third PigtoThe Wolf_5",
            "label": "answer",
            "title": "answer",
            "from": "The third Pig",
            "to": "The Wolf",
            "arrows": "to",
            "period": [
                5
            ],
            "smooth": {
                "type": "curvedCW",
                "roundness": 0.3
            }
        },
        {
            "id": "The third PigtoThe Wolf_6",
            "label": "ask",
            "title": "ask",
            "from": "The third Pig",
            "to": "The Wolf",
            "arrows": "to",
            "period": [
                6
            ],
            "smooth": {
                "type": "curvedCW",
                "roundness": 0.3
            }
        },
        {
            "id": "The third PigtoThe Wolf_7",
            "label": "frighten",
            "title": "frighten",
            "from": "The third Pig",
            "to": "The Wolf",
            "arrows": "to",
            "period": [
                7
            ],
            "smooth": {
                "type": "curvedCW",
                "roundness": 0.3
            }
        },
        {
            "id": "The third PigtoThe Wolf_8",
            "label": "eat",
            "title": "eat",
            "from": "The third Pig",
            "to": "The Wolf",
            "arrows": "to",
            "period": [
                8
            ],
            "smooth": {
                "type": "curvedCW",
                "roundness": 0.3
            }
        },
        {
            "id": "The third PigtoA Man with a load of bricks_3",
            "label": "request",
            "title": "request",
            "from": "The third Pig",
            "to": "A Man with a load of bricks",
            "arrows": "to",
            "period": [
                3
            ],
            "smooth": {
                "type": "curvedCW",
                "roundness": 0.3
            }
        },
        {
            "id": "A great round thingtoA hill_7",
            "label": "come down",
            "title": "come down",
            "from": "A great round thing",
            "to": "A hill",
            "arrows": "to",
            "period": [
                7
            ],
            "smooth": {
                "type": "curvedCW",
                "roundness": 0.3
            }
        },
        {
            "id": "The third PigtoA blazing fire_8",
            "label": "make up",
            "title": "make up",
            "from": "The third Pig",
            "to": "A blazing fire",
            "arrows": "to",
            "period": [
                8
            ],
            "smooth": {
                "type": "curvedCW",
                "roundness": 0.3
            }
        },
        {
            "id": "The third PigtoFive oclock_3",
            "label": "get up at",
            "title": "get up at",
            "from": "The third Pig",
            "to": "Five oclock",
            "arrows": "to",
            "period": [
                3
            ],
            "smooth": {
                "type": "curvedCW",
                "roundness": 0.3
            }
        },
        {
            "id": "A butter churntoA hill_6",
            "label": "turn round and roll down",
            "title": "turn round and roll down",
            "from": "A butter churn",
            "to": "A hill",
            "arrows": "to",
            "period": [
                6
            ],
            "smooth": {
                "type": "curvedCW",
                "roundness": 0.3
            }
        },
        {
            "id": "A butter churntoA hill_7",
            "label": "roll down",
            "title": "roll down",
            "from": "A butter churn",
            "to": "A hill",
            "arrows": "to",
            "period": [
                7
            ],
            "smooth": {
                "type": "curvedCW",
                "roundness": 0.3
            }
        },
        {
            "id": "The second PigtoA Man with a bundle of furze_2",
            "label": "request",
            "title": "request",
            "from": "The second Pig",
            "to": "A Man with a bundle of furze",
            "arrows": "to",
            "period": [
                2
            ],
            "smooth": {
                "type": "curvedCW",
                "roundness": 0.3
            }
        },
        {
            "id": "The second PigtoA house of furze_2",
            "label": "build",
            "title": "build",
            "from": "The second Pig",
            "to": "A house of furze",
            "arrows": "to",
            "period": [
                2
            ],
            "smooth": {
                "type": "curvedCW",
                "roundness": 0.3
            }
        },
        {
            "id": "The WolftoA chimney_8",
            "label": "come down",
            "title": "come down",
            "from": "The Wolf",
            "to": "A chimney",
            "arrows": "to",
            "period": [
                8
            ],
            "smooth": {
                "type": "curvedCW",
                "roundness": 0.3
            }
        },
        {
            "id": "A WolftoA house of straw_1",
            "label": "blow in",
            "title": "blow in",
            "from": "A Wolf",
            "to": "A house of straw",
            "arrows": "to",
            "period": [
                1
            ],
            "smooth": {
                "type": "curvedCW",
                "roundness": 0.3
            }
        },
        {
            "id": "A WolftoThe third Pig_3",
            "label": "answer",
            "title": "answer",
            "from": "A Wolf",
            "to": "The third Pig",
            "arrows": "to",
            "period": [
                3
            ],
            "smooth": {
                "type": "curvedCW",
                "roundness": 0.3
            }
        },
        {
            "id": "The third PigtoA butter churn_6",
            "label": "get into",
            "title": "get into",
            "from": "The third Pig",
            "to": "A butter churn",
            "arrows": "to",
            "period": [
                6
            ],
            "smooth": {
                "type": "curvedCW",
                "roundness": 0.3
            }
        },
        {
            "id": "The third PigtoA butter churn_7",
            "label": "get into",
            "title": "get into",
            "from": "The third Pig",
            "to": "A butter churn",
            "arrows": "to",
            "period": [
                7
            ],
            "smooth": {
                "type": "curvedCW",
                "roundness": 0.3
            }
        },
        {
            "id": "The third PigtoA field of turnips_4",
            "label": "go and come back",
            "title": "go and come back",
            "from": "The third Pig",
            "to": "A field of turnips",
            "arrows": "to",
            "period": [
                4
            ],
            "smooth": {
                "type": "curvedCW",
                "roundness": 0.3
            }
        },
        {
            "id": "The third PigtoSome apples_5",
            "label": "go for",
            "title": "go for",
            "from": "The third Pig",
            "to": "Some apples",
            "arrows": "to",
            "period": [
                5
            ],
            "smooth": {
                "type": "curvedCW",
                "roundness": 0.3
            }
        }
    ]
}